saritasa_drf_tools/__init__.py
saritasa_drf_tools/filters/__init__.py
saritasa_drf_tools/filters/django_filters.py
saritasa_drf_tools/filters/ordering.py
saritasa_drf_tools/filters/search.py
saritasa_drf_tools/open_api/__init__.py
saritasa_drf_tools/open_api/extend_schema.py
saritasa_drf_tools/open_api/serializers.py
saritasa_drf_tools/pagination.py
saritasa_drf_tools/pytest_plugin.py
saritasa_drf_tools/renderers.py
saritasa_drf_tools/serializers/__init__.py
saritasa_drf_tools/serializers/base.py
saritasa_drf_tools/serializers/mixins/__init__.py
saritasa_drf_tools/serializers/mixins/clean_validation_mixin.py
saritasa_drf_tools/serializers/mixins/field_mapping_override_mixin.py
saritasa_drf_tools/serializers/mixins/nested_fields_mixin.py
saritasa_drf_tools/serializers/mixins/user_and_request_from_request_mixin.py
saritasa_drf_tools/serializers/model_base.py
saritasa_drf_tools/testing/__init__.py
saritasa_drf_tools/testing/api_action_tester.py
saritasa_drf_tools/testing/drf_standardized_errors.py
saritasa_drf_tools/views/__init__.py
saritasa_drf_tools/views/base.py
saritasa_drf_tools/views/crud.py
saritasa_drf_tools/views/mixins/__init__.py
saritasa_drf_tools/views/mixins/permissions_map_mixin.py
saritasa_drf_tools/views/mixins/serializers_map_mixin.py
saritasa_drf_tools/views/mixins/update_without_patch_mixin.py
saritasa_drf_tools/views/read_only.py
saritasa_drf_tools-0.3.0.dist-info/METADATA
saritasa_drf_tools-0.3.0.dist-info/WHEEL
saritasa_drf_tools-0.3.0.dist-info/entry_points.txt
saritasa_drf_tools-0.3.0.dist-info/licenses/LICENCE
saritasa_drf_tools-0.3.0.dist-info/RECORD
