Metadata-Version: 2.4
Name: saritasa-drf-tools
Version: 0.3.0
Summary: Tools For DRF Used By Saritasa
License: MIT
License-File: LICENCE
Keywords: python,django,drf
Author: Saritasa
Author-email: pypi@saritasa.com
Maintainer: Stanislav Khlud
Maintainer-email: stanislav.khlud@saritasa.com
Requires-Python: >=3.12,<4.0
Classifier: Development Status :: 4 - Beta
Classifier: Framework :: Django
Classifier: Framework :: Django :: 4.2
Classifier: Framework :: Django :: 5.0
Classifier: Framework :: Django :: 5.1
Classifier: Framework :: Django :: 5.2
Classifier: Framework :: Django :: 6.0
Classifier: Framework :: Pytest
Classifier: Intended Audience :: Developers
Classifier: License :: OSI Approved :: MIT License
Classifier: Natural Language :: English
Classifier: Operating System :: OS Independent
Classifier: Programming Language :: Python :: 3
Classifier: Programming Language :: Python :: 3.12
Classifier: Programming Language :: Python :: 3.13
Classifier: Programming Language :: Python :: 3.14
Classifier: Topic :: Software Development :: Libraries :: Python Modules
Provides-Extra: all
Provides-Extra: filter
Provides-Extra: openapi
Requires-Dist: django (<7)
Requires-Dist: django-filter (<26) ; extra == "filter" or extra == "all"
Requires-Dist: djangorestframework (>=3.15.2,<4)
Requires-Dist: drf-spectacular (<1) ; extra == "openapi" or extra == "all"
Project-URL: Homepage, https://pypi.org/project/saritasa-drf-tools/
Project-URL: Repository, https://github.com/saritasa-nest/saritasa-drf-tools/
